freewheel4py/__init__.py
freewheel4py/freewheelCampaign.py
freewheel4py/freewheelCreative.py
freewheel4py/freewheelGeo.py
freewheel4py/freewheelIO.py
freewheel4py/freewheelItems.py
freewheel4py/freewheelPlacements.py
freewheel4py/impressionCap.py
freewheel4py-1.14.dist-info/METADATA
freewheel4py-1.14.dist-info/WHEEL
freewheel4py-1.14.dist-info/licenses/LICENSE
freewheel4py-1.14.dist-info/RECORD
